vyre/__init__.py
vyre/vyre.py
vyre-0.2.0.dist-info/licenses/LICENSE
vyre-0.2.0.dist-info/METADATA
vyre-0.2.0.dist-info/WHEEL
vyre-0.2.0.dist-info/entry_points.txt
vyre-0.2.0.dist-info/top_level.txt
vyre-0.2.0.dist-info/RECORD
