Metadata-Version: 2.4
Name: vyre
Version: 0.2.0
Summary: Build applications in Python with Vyre Framework.
Author: Viren Sahti
License: License & Disclaimer
Requires-Python: >=3.9
License-File: LICENSE
Dynamic: license-file
